pysecurecircuit/__init__.py
pysecurecircuit/__main__.py
pysecurecircuit/client.py
pysecurecircuit/const.py
pysecurecircuit/ot.py
pysecurecircuit/server.py
pysecurecircuit/utils.py
pysecurecircuit/circuit/__init__.py
pysecurecircuit/circuit/circuit.py
pysecurecircuit/circuit/circuit_input.py
pysecurecircuit/circuit/circuit_output.py
pysecurecircuit/circuit/functions.py
pysecurecircuit/circuit/garble_key.py
pysecurecircuit/circuit/garbled_circuit.py
pysecurecircuit/circuit/gates/__init__.py
pysecurecircuit/circuit/gates/_and.py
pysecurecircuit/circuit/gates/_or.py
pysecurecircuit/circuit/gates/_xnor.py
pysecurecircuit/circuit/gates/_xor.py
pysecurecircuit/circuit/gates/garbled_gate.py
pysecurecircuit/circuit/gates/gate.py
pysecurecircuit/circuit/gates/multiplexer.py
pysecurecircuit/secure_types/__init__.py
pysecurecircuit/secure_types/integer.py
pysecurecircuit/secure_types/wire.py
pysecurecircuit/secure_types/wires.py
pysecurecircuit-0.0.4.dist-info/LICENSE
pysecurecircuit-0.0.4.dist-info/METADATA
pysecurecircuit-0.0.4.dist-info/WHEEL
pysecurecircuit-0.0.4.dist-info/top_level.txt
pysecurecircuit-0.0.4.dist-info/RECORD
