Metadata-Version: 2.1
Name: pysecurecircuit
Version: 0.0.4
Summary: Python library for secure multi-party computation using garbled circuits
Author: Yash Amin
Author-email: yamin@hawk.iit.edu
Project-URL: Source Code, https://github.com/Yash-Amin/pySecureCircuit
Keywords: python,mpc,secure mpc,garbled circuit,multi party computation
License-File: LICENSE
Requires-Dist: attrs (==22.2.0)
Requires-Dist: Automat (==22.10.0)
Requires-Dist: black (==23.3.0)
Requires-Dist: cffi (==1.15.1)
Requires-Dist: click (==8.1.3)
Requires-Dist: constantly (==15.1.0)
Requires-Dist: cryptography (==40.0.1)
Requires-Dist: hyperlink (==21.0.0)
Requires-Dist: idna (==3.4)
Requires-Dist: incremental (==22.10.0)
Requires-Dist: mypy-extensions (==1.0.0)
Requires-Dist: packaging (==23.0)
Requires-Dist: pathspec (==0.11.1)
Requires-Dist: platformdirs (==3.2.0)
Requires-Dist: pyasn1 (==0.4.8)
Requires-Dist: pyasn1-modules (==0.2.8)
Requires-Dist: pycparser (==2.21)
Requires-Dist: pyOpenSSL (==23.1.1)
Requires-Dist: pyzmq (==25.0.2)
Requires-Dist: rsa (==4.9)
Requires-Dist: service-identity (==21.1.0)
Requires-Dist: six (==1.16.0)
Requires-Dist: tomli (==2.0.1)
Requires-Dist: typing-extensions (==4.5.0)
Requires-Dist: zope.interface (==6.0)
